setup.py
zains_gaussian_binomial_distributions/Binomialdistribution.py
zains_gaussian_binomial_distributions/Gaussiandistribution.py
zains_gaussian_binomial_distributions/Generaldistribution.py
zains_gaussian_binomial_distributions/__init__.py
zains_gaussian_binomial_distributions.egg-info/PKG-INFO
zains_gaussian_binomial_distributions.egg-info/SOURCES.txt
zains_gaussian_binomial_distributions.egg-info/dependency_links.txt
zains_gaussian_binomial_distributions.egg-info/not-zip-safe
zains_gaussian_binomial_distributions.egg-info/top_level.txt