Metadata-Version: 1.0
Name: zains-gaussian-binomial-distributions
Version: 1.0.0
Summary: Gaussian & Binomial distributions
Home-page: UNKNOWN
Author: UNKNOWN
Author-email: UNKNOWN
License: UNKNOWN
Platform: UNKNOWN
